{
  "1": {
    "class_type": "UNETLoader",
    "inputs": {
      "unet_name": "diffusion_pytorch_model-00001-of-00003.safetensors",
      "weight_dtype": "default"
    }
  },
  "2": {
    "class_type": "DualCLIPLoader",
    "inputs": {
      "clip_name1": "flux_clip_l.safetensors",
      "clip_name2": "flux_t5_1.safetensors",
      "type": "flux"
    }
  },
  "3": {
    "class_type": "VAELoader",
    "inputs": {
      "vae_name": "flux_ae.safetensors"
    }
  },
  "4": {
    "class_type": "LoraLoader",
    "inputs": {
      "model": ["1", 0],
      "clip": ["2", 0],
      "lora_name": "turnaround_sheet.safetensors",
      "strength_model": 0.8,
      "strength_clip": 0.8
    }
  },
  "5": {
    "class_type": "LoraLoader",
    "inputs": {
      "model": ["4", 0],
      "clip": ["4", 1],
      "lora_name": "baroque_fantasy_realism.safetensors",
      "strength_model": 0.7,
      "strength_clip": 0.7
    }
  },
  "6": {
    "class_type": "LoraLoader",
    "inputs": {
      "model": ["5", 0],
      "clip": ["5", 1],
      "lora_name": "velvet_mythic_flux.safetensors",
      "strength_model": 0.6,
      "strength_clip": 0.6
    }
  },
  "7": {
    "class_type": "CLIPTextEncodeFlux",
    "inputs": {
      "clip": ["6", 1],
      "clip_l": "",
      "t5xxl": "",
      "guidance": 3.5
    }
  },
  "8": {
    "class_type": "CLIPTextEncodeFlux",
    "inputs": {
      "clip": ["6", 1],
      "clip_l": "",
      "t5xxl": "",
      "guidance": 3.5
    }
  },
  "9": {
    "class_type": "EmptyLatentImage",
    "inputs": {
      "width": 1024,
      "height": 1024,
      "batch_size": 1
    }
  },
  "10": {
    "class_type": "KSampler",
    "inputs": {
      "model": ["6", 0],
      "seed": 0,
      "steps": 28,
      "cfg": 1.0,
      "sampler_name": "euler",
      "scheduler": "simple",
      "denoise": 1.0,
      "positive": ["7", 0],
      "negative": ["8", 0],
      "latent_image": ["9", 0]
    }
  },
  "11": {
    "class_type": "VAEDecode",
    "inputs": {
      "samples": ["10", 0],
      "vae": ["3", 0]
    }
  },
  "12": {
    "class_type": "SaveImage",
    "inputs": {
      "filename_prefix": "foulward_turnaround",
      "images": ["11", 0]
    }
  }
}
